tetris.py
tt_backend.py
tt_panel.py
tt_tetro.py
TermTetris-0.9.9.dist-info/LICENSE
TermTetris-0.9.9.dist-info/METADATA
TermTetris-0.9.9.dist-info/WHEEL
TermTetris-0.9.9.dist-info/entry_points.txt
TermTetris-0.9.9.dist-info/top_level.txt
TermTetris-0.9.9.dist-info/RECORD
