Metadata-Version: 2.1
Name: TermTetris
Version: 0.9.9
Summary: A Tetris game in character terminal environment
Author-email: Brooks Su <yipeng00@gmail.com>
License: Apache License
Project-URL: Homepage, https://github.com/brookssu/TermTetris
Keywords: tetris,termtetris,game,terminal,ltermio
Classifier: License :: OSI Approved :: Apache Software License
Classifier: Natural Language :: English
Classifier: Operating System :: Unix
Classifier: Operating System :: POSIX
Classifier: Operating System :: MacOS :: MacOS X
Classifier: Programming Language :: Python :: 3.6
Classifier: Environment :: Console
Classifier: Development Status :: 4 - Beta
Classifier: Intended Audience :: End Users/Desktop
Classifier: Topic :: Games/Entertainment
Requires-Python: >=3.6
License-File: LICENSE
Requires-Dist: ltermio
